HamiltonIO/__init__.py
HamiltonIO/hamiltonian.py
HamiltonIO/lcao_hamiltonian.py
HamiltonIO/orbital.py
HamiltonIO/print_hamiltonian.py
HamiltonIO/utils.py
HamiltonIO/abacus/__init__.py
HamiltonIO/abacus/abacus_api.py
HamiltonIO/abacus/abacus_wrapper.py
HamiltonIO/abacus/cli.py
HamiltonIO/abacus/orbital_api.py
HamiltonIO/abacus/stru_api.py
HamiltonIO/abacus/test_read_HRSR.py
HamiltonIO/abacus/test_read_stru.py
HamiltonIO/epw/__init__.py
HamiltonIO/epw/cli.py
HamiltonIO/epw/epc.py
HamiltonIO/epw/epw_netcdf.py
HamiltonIO/epw/epwparser.py
HamiltonIO/epw/example_epwparser.py
HamiltonIO/epw/example_usage.py
HamiltonIO/epw/plot.py
HamiltonIO/epw/remove_down_suffix.py
HamiltonIO/epw/test_wigner.py
HamiltonIO/epw/wigner.py
HamiltonIO/format/spmat.py
HamiltonIO/gpaw/lcao_ham.py
HamiltonIO/lawaf/__init__.py
HamiltonIO/lawaf/electron_wannier.py
HamiltonIO/mathutils/__init__.py
HamiltonIO/mathutils/kR_convert.py
HamiltonIO/mathutils/lowdin.py
HamiltonIO/mathutils/pauli.py
HamiltonIO/mathutils/rotate_spin.py
HamiltonIO/model/__init__.py
HamiltonIO/model/density_matrix.py
HamiltonIO/model/fermi.py
HamiltonIO/model/kR_convert.py
HamiltonIO/model/occupations.py
HamiltonIO/siesta/__init__.py
HamiltonIO/siesta/cli.py
HamiltonIO/siesta/mysiesta_nc.py
HamiltonIO/siesta/sisl_wrapper.py
HamiltonIO/wannier/__init__.py
HamiltonIO/wannier/cli.py
HamiltonIO/wannier/myTB.py
HamiltonIO/wannier/plot.py
HamiltonIO/wannier/utils.py
HamiltonIO/wannier/w90_parser.py
HamiltonIO/wannier/w90_tb_parser.py
HamiltonIO/wannier/wannier_hamiltonian.py
HamiltonIO/wantibexos/H_extract-siesta.py
HamiltonIO/wantibexos/output_wantibexos.py
hamiltonio-0.3.2.dist-info/licenses/LICENSE
hamiltonio-0.3.2.dist-info/METADATA
hamiltonio-0.3.2.dist-info/WHEEL
hamiltonio-0.3.2.dist-info/entry_points.txt
hamiltonio-0.3.2.dist-info/top_level.txt
hamiltonio-0.3.2.dist-info/RECORD
